webcraft/__init__.py
webcraft/apiview.py
webcraft/admin/__init__.py
webcraft/admin/classbased.py
webcraft/admin/saform.py
webcraft-0.2.0.dist-info/METADATA
webcraft-0.2.0.dist-info/RECORD
webcraft-0.2.0.dist-info/WHEEL
webcraft-0.2.0.dist-info/top_level.txt
